numplot/__init__.py
numplot/task_1.py
numplot/task_2.py
numplot/task_3.py
numplot/task_4.py
numplot/task_5.py
numplot/task_5_1.py
numplot/task_5_2.py
numplot/task_5_3.py
numplot-1.0.0.dist-info/METADATA
numplot-1.0.0.dist-info/WHEEL
numplot-1.0.0.dist-info/top_level.txt
numplot-1.0.0.dist-info/RECORD
