Metadata-Version: 2.2
Name: numplot
Version: 1.0.0
Summary: Package mathstats contains mathematical and statistical functions, distributions, tests
Author: amogusbazed
Author-email: amogusbazed@gmail.com
Keywords: files speedfiles
Classifier: Programming Language :: Python :: 3.13
Classifier: License :: OSI Approved :: MIT License
Classifier: Operating System :: OS Independent
Requires-Python: >=3.6
Dynamic: author
Dynamic: author-email
Dynamic: classifier
Dynamic: description
Dynamic: description-content-type
Dynamic: keywords
Dynamic: requires-python
Dynamic: summary
